ximage/__init__.py
ximage/__main__.py
ximage/convert_image.py
ximage/exceptions.py
ximage/resize_image.py
ximage/utils.py
ximage-0.3.1.dist-info/LICENSE
ximage-0.3.1.dist-info/METADATA
ximage-0.3.1.dist-info/WHEEL
ximage-0.3.1.dist-info/entry_points.txt
ximage-0.3.1.dist-info/top_level.txt
ximage-0.3.1.dist-info/RECORD
