Metadata-Version: 2.1
Name: ximage
Version: 0.3.1
Summary: a simple image process tool.
Home-page: https://github.com/a358003542/ximage
Author: cdwanze
Author-email: a358003542@gmail.com
License: MIT
Keywords: ximage,python
Platform: Linux
Platform: windows
Classifier: License :: OSI Approved :: MIT License
Classifier: Operating System :: Microsoft
Classifier: Operating System :: POSIX :: Linux
Classifier: Programming Language :: Python :: 3
Requires-Dist: pillow
Requires-Dist: click
